LICENSE.txt
MANIFEST.in
README.md
pyproject.toml
setup.cfg
setup.py
C:/Users/alberiba/MyDrive/Workspace/Other/Pyfhel/Pyfhel/Afhel/Afseal.cpp
Pyfhel/PyCtxt.pxd
Pyfhel/PyCtxt.pyx
Pyfhel/PyPoly.pxd
Pyfhel/PyPoly.pyx
Pyfhel/PyPtxt.pxd
Pyfhel/PyPtxt.pyx
Pyfhel/Pyfhel.pxd
Pyfhel/Pyfhel.pyx
Pyfhel/__init__.py
Pyfhel.egg-info/PKG-INFO
Pyfhel.egg-info/SOURCES.txt
Pyfhel.egg-info/dependency_links.txt
Pyfhel.egg-info/not-zip-safe
Pyfhel.egg-info/requires.txt
Pyfhel.egg-info/top_level.txt
Pyfhel/Afhel/Afhel.h
Pyfhel/Afhel/Afhel.pxd
Pyfhel/Afhel/Afseal.cpp
Pyfhel/Afhel/Afseal.h
Pyfhel/backend/SEAL/.clang-format
Pyfhel/backend/SEAL/.git
Pyfhel/backend/SEAL/.gitignore
Pyfhel/backend/SEAL/.pre-commit-config.yaml
Pyfhel/backend/SEAL/CHANGES.md
Pyfhel/backend/SEAL/CMakeLists.txt
Pyfhel/backend/SEAL/CODE_OF_CONDUCT.md
Pyfhel/backend/SEAL/CONTRIBUTING.md
Pyfhel/backend/SEAL/ISSUES.md
Pyfhel/backend/SEAL/LICENSE
Pyfhel/backend/SEAL/NOTICE
Pyfhel/backend/SEAL/README.md
Pyfhel/backend/SEAL/SECURITY.md
Pyfhel/backend/SEAL/android/.gitignore
Pyfhel/backend/SEAL/android/build.gradle
Pyfhel/backend/SEAL/android/gradle.properties
Pyfhel/backend/SEAL/android/gradlew
Pyfhel/backend/SEAL/android/gradlew.bat
Pyfhel/backend/SEAL/android/settings.gradle
Pyfhel/backend/SEAL/android/app/.gitignore
Pyfhel/backend/SEAL/android/app/build.gradle
Pyfhel/backend/SEAL/android/app/proguard-rules.pro
Pyfhel/backend/SEAL/android/app/src/main/AndroidManifest.xml
Pyfhel/backend/SEAL/android/app/src/main/res/drawable/ic_launcher_background.xml
Pyfhel/backend/SEAL/android/app/src/main/res/drawable-v24/ic_launcher_foreground.xml
Pyfhel/backend/SEAL/android/app/src/main/res/mipmap-anydpi-v26/ic_launcher.xml
Pyfhel/backend/SEAL/android/app/src/main/res/mipmap-anydpi-v26/ic_launcher_round.xml
Pyfhel/backend/SEAL/android/app/src/main/res/mipmap-hdpi/ic_launcher.png
Pyfhel/backend/SEAL/android/app/src/main/res/mipmap-hdpi/ic_launcher_round.png
Pyfhel/backend/SEAL/android/app/src/main/res/mipmap-mdpi/ic_launcher.png
Pyfhel/backend/SEAL/android/app/src/main/res/mipmap-mdpi/ic_launcher_round.png
Pyfhel/backend/SEAL/android/app/src/main/res/mipmap-xhdpi/ic_launcher.png
