Metadata-Version: 2.1
Name: Pyfhel
Version: 3.4.1
Summary: Python for Homomorphic Encryption Libraries
Home-page: https://pyfhel.readthedocs.io
Download-URL: https://github.com/ibarrond/github
Author: Alberto Ibarrondo, Alexander Viand
Author-email: Alberto Ibarrondo <ibarrond@eurecom.fr>, Alexander Viand <alexander.viand@inf.ethz.ch>
License: GNU GPLv3
Project-URL: homepage, https://pyfhel.readthedocs.io
Project-URL: documentation, https://pyfhel.readthedocs.io
Project-URL: repository, https://github.com/ibarrond/github
Keywords: homomorphic,encryption,cython,cryptography
Platform: Darwin
Classifier: Programming Language :: C++
Classifier: Programming Language :: Cython
Classifier: Programming Language :: Python :: 3
Classifier: Programming Language :: Python :: 3.7
Classifier: Programming Language :: Python :: 3.8
Classifier: Programming Language :: Python :: 3.9
Classifier: Programming Language :: Python :: 3.10
Classifier: Programming Language :: Python :: Implementation :: CPython
Classifier: Development Status :: 5 - Production/Stable
Classifier: License :: OSI Approved :: GNU General Public License v3 (GPLv3)
Classifier: Operating System :: Unix
Classifier: Operating System :: POSIX
Classifier: Operating System :: Microsoft :: Windows
Classifier: Topic :: Security
Classifier: Topic :: Security :: Cryptography
Requires-Python: >=3.7
Provides-Extra: test
License-File: LICENSE.txt
